{
    "os": "Linux-5.15.0-125-generic-x86_64-with-debian-bookworm-sid",
    "python": "3.6.13",
    "heartbeatAt": "2025-03-14T12:56:34.397690",
    "startedAt": "2025-03-14T12:56:33.128172",
    "docker": null,
    "cuda": null,
    "args": [
        "2",
        "4D.json",
        "-t",
        "512",
        "-c",
        "2",
        "-e",
        "250",
        "--limcols",
        "--test",
        "--sweep"
    ],
    "state": "running",
    "program": "main.py",
    "codePath": "main.py",
    "git": {
        "remote": "https://github.com/yokko123/4D-mJ-Net.git",
        "commit": "bf9da0659f1ec4becd26977d03e71ee83b5715f7"
    },
    "email": null,
    "root": "/mnt/beegfs/home/sazidur/4D-mJ-Net",
    "host": "gorina9",
    "username": "sazidur",
    "executable": "/bhome/sazidur/miniconda3/envs/tf2_gpu/bin/python3.6",
    "cpu_count": 128,
    "cpu_count_logical": 128,
    "cpu_freq": {
        "current": 1715.1894375000002,
        "min": 1500.0,
        "max": 2450.0
    },
    "cpu_freq_per_core": [
        {
            "current": 3099.442,
            "min": 1500.0,
            "max": 2450.0
        },
        {
            "current": 1500.0,
            "min": 1500.0,
            "max": 2450.0
        },
        {
            "current": 1500.0,
            "min": 1500.0,
            "max": 2450.0
        },
        {
            "current": 1500.0,
            "min": 1500.0,
            "max": 2450.0
        },
        {
            "current": 1500.0,
            "min": 1500.0,
            "max": 2450.0
        },
        {
            "current": 1500.0,
            "min": 1500.0,
            "max": 2450.0
        },
        {
            "current": 2450.0,
            "min": 1500.0,
            "max": 2450.0
        },
        {
            "current": 1500.0,
            "min": 1500.0,
            "max": 2450.0
        },
        {
            "current": 1500.0,
            "min": 1500.0,
            "max": 2450.0
        },
        {
            "current": 1500.0,
            "min": 1500.0,
            "max": 2450.0
        },
        {
            "current": 1500.0,
            "min": 1500.0,
            "max": 2450.0
        },
        {
            "current": 2479.595,
            "min": 1500.0,
            "max": 2450.0
        },
        {
            "current": 3099.7,
            "min": 1500.0,
            "max": 2450.0
        },
        {
            "current": 1500.0,
            "min": 1500.0,
            "max": 2450.0
        },
        {
            "current": 1500.0,
            "min": 1500.0,
            "max": 2450.0
        },
        {
            "current": 1500.0,
            "min": 1500.0,
            "max": 2450.0
        },
        {
            "current": 2450.0,
            "min": 1500.0,
            "max": 2450.0
        },
        {
            "current": 2450.0,
            "min": 1500.0,
            "max": 2450.0
        },
        {
            "current": 2450.0,
            "min": 1500.0,
            "max": 2450.0
        },
        {
            "current": 2000.0,
            "min": 1500.0,
            "max": 2450.0
        },
        {
            "current": 2450.0,
            "min": 1500.0,
            "max": 2450.0
        },
        {
            "current": 2450.0,
            "min": 1500.0,
            "max": 2450.0
        },
        {
            "current": 2450.0,
            "min": 1500.0,
            "max": 2450.0
        },
        {
            "current": 2450.0,
            "min": 1500.0,
            "max": 2450.0
        },
        {
            "current": 1500.0,
            "min": 1500.0,
            "max": 2450.0
        },
        {
            "current": 3099.472,
            "min": 1500.0,
            "max": 2450.0
        },
        {
            "current": 2450.0,
            "min": 1500.0,
            "max": 2450.0
        },
        {
            "current": 2450.0,
            "min": 1500.0,
            "max": 2450.0
        },
        {
            "current": 3099.6,
            "min": 1500.0,
            "max": 2450.0
        },
        {
            "current": 3099.451,
            "min": 1500.0,
            "max": 2450.0
        },
        {
            "current": 1500.0,
            "min": 1500.0,
            "max": 2450.0
        },
        {
            "current": 1500.0,
            "min": 1500.0,
            "max": 2450.0
        },
        {
            "current": 1500.0,
            "min": 1500.0,
            "max": 2450.0
        },
        {
            "current": 1500.0,
            "min": 1500.0,
            "max": 2450.0
        },
        {
            "current": 2450.0,
            "min": 1500.0,
            "max": 2450.0
        },
        {
            "current": 1500.0,
            "min": 1500.0,
            "max": 2450.0
        },
        {
            "current": 1500.0,
            "min": 1500.0,
            "max": 2450.0
        },
        {
            "current": 1500.0,
            "min": 1500.0,
            "max": 2450.0
        },
        {
            "current": 1500.0,
            "min": 1500.0,
            "max": 2450.0
        },
        {
            "current": 3099.888,
            "min": 1500.0,
            "max": 2450.0
        },
        {
            "current": 1500.0,
            "min": 1500.0,
            "max": 2450.0
        },
        {
            "current": 1500.0,
            "min": 1500.0,
            "max": 2450.0
        },
        {
            "current": 1500.0,
            "min": 1500.0,
            "max": 2450.0
        },
        {
            "current": 1500.0,
            "min": 1500.0,
            "max": 2450.0
        },
        {
            "current": 1500.0,
            "min": 1500.0,
            "max": 2450.0
        },
        {
            "current": 1500.0,
            "min": 1500.0,
            "max": 2450.0
        },
        {
            "current": 1500.0,
            "min": 1500.0,
            "max": 2450.0
        },
        {
            "current": 1500.0,
            "min": 1500.0,
            "max": 2450.0
        },
        {
            "current": 1500.0,
            "min": 1500.0,
            "max": 2450.0
        },
        {
            "current": 1500.0,
            "min": 1500.0,
            "max": 2450.0
        },
        {
            "current": 1500.0,
            "min": 1500.0,
            "max": 2450.0
        },
        {
            "current": 1500.0,
            "min": 1500.0,
            "max": 2450.0
        },
        {
            "current": 1500.0,
            "min": 1500.0,
            "max": 2450.0
        },
        {
            "current": 1500.0,
            "min": 1500.0,
            "max": 2450.0
        },
        {
            "current": 1500.0,
            "min": 1500.0,
            "max": 2450.0
        },
        {
            "current": 1500.0,
            "min": 1500.0,
            "max": 2450.0
        },
        {
            "current": 1500.0,
            "min": 1500.0,
            "max": 2450.0
        },
        {
            "current": 1500.0,
            "min": 1500.0,
            "max": 2450.0
        },
        {
            "current": 1500.0,
            "min": 1500.0,
            "max": 2450.0
        },
        {
            "current": 1500.0,
            "min": 1500.0,
            "max": 2450.0
        },
        {
            "current": 1500.0,
            "min": 1500.0,
            "max": 2450.0
        },
        {
            "current": 1500.0,
            "min": 1500.0,
            "max": 2450.0
        },
        {
            "current": 1500.0,
            "min": 1500.0,
            "max": 2450.0
        },
        {
            "current": 1500.0,
            "min": 1500.0,
            "max": 2450.0
        },
        {
            "current": 1500.0,
            "min": 1500.0,
            "max": 2450.0
        },
        {
            "current": 2000.0,
            "min": 1500.0,
            "max": 2450.0
        },
        {
            "current": 1500.0,
            "min": 1500.0,
            "max": 2450.0
        },
        {
            "current": 1500.0,
            "min": 1500.0,
            "max": 2450.0
        },
        {
            "current": 3099.494,
            "min": 1500.0,
            "max": 2450.0
        },
        {
            "current": 1500.0,
            "min": 1500.0,
            "max": 2450.0
        },
        {
            "current": 1500.0,
            "min": 1500.0,
            "max": 2450.0
        },
        {
            "current": 1500.0,
            "min": 1500.0,
            "max": 2450.0
        },
        {
            "current": 1500.0,
            "min": 1500.0,
            "max": 2450.0
        },
        {
            "current": 1500.0,
            "min": 1500.0,
            "max": 2450.0
        },
        {
            "current": 1500.0,
            "min": 1500.0,
            "max": 2450.0
        },
        {
            "current": 2450.0,
            "min": 1500.0,
            "max": 2450.0
        },
        {
            "current": 1500.0,
            "min": 1500.0,
            "max": 2450.0
        },
        {
            "current": 1500.0,
            "min": 1500.0,
            "max": 2450.0
        },
        {
            "current": 1500.0,
            "min": 1500.0,
            "max": 2450.0
        },
        {
            "current": 1500.0,
            "min": 1500.0,
            "max": 2450.0
        },
        {
            "current": 1500.0,
            "min": 1500.0,
            "max": 2450.0
        },
        {
            "current": 1500.0,
            "min": 1500.0,
            "max": 2450.0
        },
        {
            "current": 1500.0,
            "min": 1500.0,
            "max": 2450.0
        },
        {
            "current": 1500.0,
            "min": 1500.0,
            "max": 2450.0
        },
        {
            "current": 1500.0,
            "min": 1500.0,
            "max": 2450.0
        },
        {
            "current": 1500.0,
            "min": 1500.0,
            "max": 2450.0
        },
        {
            "current": 1500.0,
            "min": 1500.0,
            "max": 2450.0
        },
        {
            "current": 1500.0,
            "min": 1500.0,
            "max": 2450.0
        },
        {
            "current": 2450.0,
            "min": 1500.0,
            "max": 2450.0
        },
        {
            "current": 2450.0,
            "min": 1500.0,
            "max": 2450.0
        },
        {
            "current": 1500.0,
            "min": 1500.0,
            "max": 2450.0
        },
        {
            "current": 1500.0,
            "min": 1500.0,
            "max": 2450.0
        },
        {
            "current": 3099.748,
            "min": 1500.0,
            "max": 2450.0
        },
        {
            "current": 1500.0,
            "min": 1500.0,
            "max": 2450.0
        },
        {
            "current": 1500.0,
            "min": 1500.0,
            "max": 2450.0
        },
        {
            "current": 1500.0,
            "min": 1500.0,
            "max": 2450.0
        },
        {
            "current": 1500.0,
            "min": 1500.0,
            "max": 2450.0
        },
        {
            "current": 1500.0,
            "min": 1500.0,
            "max": 2450.0
        },
        {
            "current": 1500.0,
            "min": 1500.0,
            "max": 2450.0
        },
        {
            "current": 1500.0,
            "min": 1500.0,
            "max": 2450.0
        },
        {
            "current": 1500.0,
            "min": 1500.0,
            "max": 2450.0
        },
        {
            "current": 1500.0,
            "min": 1500.0,
            "max": 2450.0
        },
        {
            "current": 1500.0,
            "min": 1500.0,
            "max": 2450.0
        },
        {
            "current": 2450.0,
            "min": 1500.0,
            "max": 2450.0
        },
        {
            "current": 1500.0,
            "min": 1500.0,
            "max": 2450.0
        },
        {
            "current": 1500.0,
            "min": 1500.0,
            "max": 2450.0
        },
        {
            "current": 1500.0,
            "min": 1500.0,
            "max": 2450.0
        },
        {
            "current": 1500.0,
            "min": 1500.0,
            "max": 2450.0
        },
        {
            "current": 1500.0,
            "min": 1500.0,
            "max": 2450.0
        },
        {
            "current": 1500.0,
            "min": 1500.0,
            "max": 2450.0
        },
        {
            "current": 1500.0,
            "min": 1500.0,
            "max": 2450.0
        },
        {
            "current": 1500.0,
            "min": 1500.0,
            "max": 2450.0
        },
        {
            "current": 1500.0,
            "min": 1500.0,
            "max": 2450.0
        },
        {
            "current": 1500.0,
            "min": 1500.0,
            "max": 2450.0
        },
        {
            "current": 1500.0,
            "min": 1500.0,
            "max": 2450.0
        },
        {
            "current": 1500.0,
            "min": 1500.0,
            "max": 2450.0
        },
        {
            "current": 1500.0,
            "min": 1500.0,
            "max": 2450.0
        },
        {
            "current": 1500.0,
            "min": 1500.0,
            "max": 2450.0
        },
        {
            "current": 1500.0,
            "min": 1500.0,
            "max": 2450.0
        },
        {
            "current": 1500.0,
            "min": 1500.0,
            "max": 2450.0
        },
        {
            "current": 1500.0,
            "min": 1500.0,
            "max": 2450.0
        },
        {
            "current": 1500.0,
            "min": 1500.0,
            "max": 2450.0
        },
        {
            "current": 1500.0,
            "min": 1500.0,
            "max": 2450.0
        },
        {
            "current": 1500.0,
            "min": 1500.0,
            "max": 2450.0
        },
        {
            "current": 1500.0,
            "min": 1500.0,
            "max": 2450.0
        },
        {
            "current": 1500.0,
            "min": 1500.0,
            "max": 2450.0
        },
        {
            "current": 1500.0,
            "min": 1500.0,
            "max": 2450.0
        },
        {
            "current": 1500.0,
            "min": 1500.0,
            "max": 2450.0
        }
    ],
    "disk": {
        "total": 183.01606369018555,
        "used": 28.292293548583984
    },
    "gpu": "NVIDIA A100 80GB PCIe",
    "gpu_count": 8,
    "gpu_devices": [
        {
            "name": "NVIDIA A100 80GB PCIe",
            "memory_total": 85899345920
        },
        {
            "name": "NVIDIA A100 80GB PCIe",
            "memory_total": 85899345920
        },
        {
            "name": "NVIDIA A100 80GB PCIe",
            "memory_total": 85899345920
        },
        {
            "name": "NVIDIA A100 80GB PCIe",
            "memory_total": 85899345920
        },
        {
            "name": "NVIDIA A100 80GB PCIe",
            "memory_total": 85899345920
        },
        {
            "name": "NVIDIA A100 80GB PCIe",
            "memory_total": 85899345920
        },
        {
            "name": "NVIDIA H100 NVL",
            "memory_total": 100485038080
        },
        {
            "name": "NVIDIA H100 NVL",
            "memory_total": 100485038080
        }
    ],
    "memory": {
        "total": 2003.8929443359375
    }
}
